contextif/__init__.py
contextif/py.typed
contextif/state.py
contextif/variable.py
contextif-0.0.5.dist-info/LICENSE
contextif-0.0.5.dist-info/METADATA
contextif-0.0.5.dist-info/WHEEL
contextif-0.0.5.dist-info/top_level.txt
contextif-0.0.5.dist-info/RECORD
