Metadata-Version: 2.1
Name: contextif
Version: 0.0.5
Summary: Run the function only in a specific context
Author-email: Evgeniy Blinov <zheni-b@yandex.ru>
Project-URL: Source, https://github.com/pomponchik/contextif
Project-URL: Tracker, https://github.com/pomponchik/contextif/issues
Classifier: Operating System :: OS Independent
Classifier: Operating System :: MacOS :: MacOS X
Classifier: Operating System :: Microsoft :: Windows
Classifier: Operating System :: POSIX
Classifier: Operating System :: POSIX :: Linux
Classifier: Programming Language :: Python :: 3.7
Classifier: Programming Language :: Python :: 3.8
Classifier: Programming Language :: Python :: 3.9
Classifier: Programming Language :: Python :: 3.10
Classifier: Programming Language :: Python :: 3.11
Classifier: Programming Language :: Python :: 3.12
Classifier: License :: OSI Approved :: MIT License
Classifier: Intended Audience :: Developers
Classifier: Topic :: Software Development :: Libraries
Requires-Python: >=3.7
License-File: LICENSE
Requires-Dist: typing-extensions
